edgegap_logging/__init__.py
edgegap_logging/_configuration.py
edgegap_logging/_context_logger.py
edgegap_logging/_contexts/__init__.py
edgegap_logging/_contexts/_contexts.py
edgegap_logging/_contexts/_http_header.py
edgegap_logging/_format.py
edgegap_logging/_logging.py
edgegap_logging/_v1_context_logger.py
edgegap_logging-1.12.12.dist-info/LICENSE
edgegap_logging-1.12.12.dist-info/METADATA
edgegap_logging-1.12.12.dist-info/WHEEL
edgegap_logging-1.12.12.dist-info/RECORD
