Metadata-Version: 2.1
Name: edgegap-logging
Version: 1.12.12
Summary: The Edgegap Logging library includes various tools and helpers for interacting with Standard Logging Formatter and Colored Logs. It is designed for use within the Edgegap organization.
Author: Bastien Roy
Author-email: bastien@edgegap.com
Requires-Python: >=3.10,<4.0
Classifier: Programming Language :: Python :: 3
Classifier: Programming Language :: Python :: 3.10
Classifier: Programming Language :: Python :: 3.11
Classifier: Programming Language :: Python :: 3.12
Requires-Dist: colorama (>=0.4.6,<0.5.0)
Requires-Dist: pydantic (>=2.7.1,<3.0.0)
